algoxtools/__init__.py
algoxtools-0.1.5.dist-info/LICENSE
algoxtools-0.1.5.dist-info/METADATA
algoxtools-0.1.5.dist-info/WHEEL
algoxtools-0.1.5.dist-info/top_level.txt
algoxtools-0.1.5.dist-info/RECORD
