Metadata-Version: 2.1
Name: algoxtools
Version: 0.1.5
Summary: A Fast Algorithm X implementation in Python using Numpy and Numba
Home-page: https://github.com/Seemee/algoxtools
Author: Symen Hovinga
Author-email: itsfull@hotmail.com
License: UNKNOWN
Platform: UNKNOWN
Classifier: Development Status :: 2 - Pre-Alpha
Classifier: Programming Language :: Python :: 2
Classifier: Programming Language :: Python :: 3
Classifier: License :: OSI Approved :: MIT License
Classifier: Operating System :: OS Independent
Requires-Dist: numpy
Requires-Dist: numba
